{
 "cells": [
  {
   "cell_type": "code",
   "execution_count": null,
   "id": "75cd0127-3d5b-4dd6-96a9-7fcacdc12e34",
   "metadata": {},
   "outputs": [],
   "source": [
    "{\n",
    "  \"annotations\": {\n",
    "    \"list\": [\n",
    "      {\n",
    "        \"builtIn\": 1,\n",
    "        \"datasource\": {\n",
    "          \"type\": \"grafana\",\n",
    "          \"uid\": \"-- Grafana --\"\n",
    "        },\n",
    "        \"enable\": true,\n",
    "        \"hide\": true,\n",
    "        \"iconColor\": \"rgba(0, 211, 255, 1)\",\n",
    "        \"name\": \"Annotations & Alerts\",\n",
    "        \"type\": \"dashboard\"\n",
    "      }\n",
    "    ]\n",
    "  },\n",
    "  \"editable\": true,\n",
    "  \"fiscalYearStartMonth\": 0,\n",
    "  \"graphTooltip\": 0,\n",
    "  \"links\": [],\n",
    "  \"panels\": [\n",
    "    {\n",
    "      \"datasource\": {\n",
    "        \"type\": \"grafana-postgresql-datasource\",\n",
    "        \"uid\": \"bfhu70iltl8n4e\"\n",
    "      },\n",
    "      \"fieldConfig\": {\n",
    "        \"defaults\": {\n",
    "          \"color\": {\n",
    "            \"mode\": \"thresholds\"\n",
    "          },\n",
    "          \"decimals\": 0,\n",
    "          \"mappings\": [],\n",
    "          \"thresholds\": {\n",
    "            \"mode\": \"absolute\",\n",
    "            \"steps\": [\n",
    "              {\n",
    "                \"color\": \"green\",\n",
    "                \"value\": 0\n",
    "              }\n",
    "            ]\n",
    "          }\n",
    "        },\n",
    "        \"overrides\": []\n",
    "      },\n",
    "      \"gridPos\": {\n",
    "        \"h\": 5,\n",
    "        \"w\": 4,\n",
    "        \"x\": 0,\n",
    "        \"y\": 0\n",
    "      },\n",
    "      \"id\": 1,\n",
    "      \"options\": {\n",
    "        \"colorMode\": \"none\",\n",
    "        \"graphMode\": \"area\",\n",
    "        \"justifyMode\": \"auto\",\n",
    "        \"orientation\": \"auto\",\n",
    "        \"percentChangeColorMode\": \"standard\",\n",
    "        \"reduceOptions\": {\n",
    "          \"calcs\": [\n",
    "            \"lastNotNull\"\n",
    "          ],\n",
    "          \"fields\": \"\",\n",
    "          \"values\": false\n",
    "        },\n",
    "        \"showPercentChange\": false,\n",
    "        \"textMode\": \"auto\",\n",
    "        \"wideLayout\": true\n",
    "      },\n",
    "      \"pluginVersion\": \"12.4.2\",\n",
    "      \"targets\": [\n",
    "        {\n",
    "          \"dataset\": \"erp_db\",\n",
    "          \"datasource\": {\n",
    "            \"type\": \"grafana-postgresql-datasource\",\n",
    "            \"uid\": \"bfhu70iltl8n4e\"\n",
    "          },\n",
    "          \"editorMode\": \"code\",\n",
    "          \"format\": \"table\",\n",
    "          \"rawQuery\": true,\n",
    "          \"rawSql\": \"SELECT COUNT(*) AS total_orders\\nFROM orders_data;\",\n",
    "          \"refId\": \"A\",\n",
    "          \"sql\": {\n",
    "            \"columns\": [\n",
    "              {\n",
    "                \"parameters\": [],\n",
    "                \"type\": \"function\"\n",
    "              }\n",
    "            ],\n",
    "            \"groupBy\": [\n",
    "              {\n",
    "                \"property\": {\n",
    "                  \"type\": \"string\"\n",
    "                },\n",
    "                \"type\": \"groupBy\"\n",
    "              }\n",
    "            ],\n",
    "            \"limit\": 50\n",
    "          }\n",
    "        }\n",
    "      ],\n",
    "      \"title\": \"Total orders\",\n",
    "      \"type\": \"stat\"\n",
    "    },\n",
    "    {\n",
    "      \"datasource\": {\n",
    "        \"type\": \"grafana-postgresql-datasource\",\n",
    "        \"uid\": \"bfhu70iltl8n4e\"\n",
    "      },\n",
    "      \"fieldConfig\": {\n",
    "        \"defaults\": {\n",
    "          \"color\": {\n",
    "            \"mode\": \"thresholds\"\n",
    "          },\n",
    "          \"decimals\": 0,\n",
    "          \"mappings\": [],\n",
    "          \"thresholds\": {\n",
    "            \"mode\": \"absolute\",\n",
    "            \"steps\": [\n",
    "              {\n",
    "                \"color\": \"green\",\n",
    "                \"value\": 0\n",
    "              },\n",
    "              {\n",
    "                \"color\": \"red\",\n",
    "                \"value\": 80\n",
    "              }\n",
    "            ]\n",
    "          },\n",
    "          \"unit\": \"currencyUSD\"\n",
    "        },\n",
    "        \"overrides\": []\n",
    "      },\n",
    "      \"gridPos\": {\n",
    "        \"h\": 5,\n",
    "        \"w\": 5,\n",
    "        \"x\": 4,\n",
    "        \"y\": 0\n",
    "      },\n",
    "      \"id\": 2,\n",
    "      \"options\": {\n",
    "        \"colorMode\": \"none\",\n",
    "        \"graphMode\": \"area\",\n",
    "        \"justifyMode\": \"auto\",\n",
    "        \"orientation\": \"auto\",\n",
    "        \"percentChangeColorMode\": \"standard\",\n",
    "        \"reduceOptions\": {\n",
    "          \"calcs\": [\n",
    "            \"lastNotNull\"\n",
    "          ],\n",
    "          \"fields\": \"\",\n",
    "          \"values\": false\n",
    "        },\n",
    "        \"showPercentChange\": false,\n",
    "        \"textMode\": \"auto\",\n",
    "        \"wideLayout\": true\n",
    "      },\n",
    "      \"pluginVersion\": \"12.4.2\",\n",
    "      \"targets\": [\n",
    "        {\n",
    "          \"dataset\": \"erp_db\",\n",
    "          \"editorMode\": \"code\",\n",
    "          \"format\": \"table\",\n",
    "          \"rawQuery\": true,\n",
    "          \"rawSql\": \"SELECT SUM(order_total_value) AS total_revenue\\nFROM orders_data;\",\n",
    "          \"refId\": \"A\",\n",
    "          \"sql\": {\n",
    "            \"columns\": [\n",
    "              {\n",
    "                \"parameters\": [],\n",
    "                \"type\": \"function\"\n",
    "              }\n",
    "            ],\n",
    "            \"groupBy\": [\n",
    "              {\n",
    "                \"property\": {\n",
    "                  \"type\": \"string\"\n",
    "                },\n",
    "                \"type\": \"groupBy\"\n",
    "              }\n",
    "            ],\n",
    "            \"limit\": 50\n",
    "          }\n",
    "        }\n",
    "      ],\n",
    "      \"title\": \"Total Revenue\",\n",
    "      \"type\": \"stat\"\n",
    "    },\n",
    "    {\n",
    "      \"datasource\": {\n",
    "        \"type\": \"grafana-postgresql-datasource\",\n",
    "        \"uid\": \"bfhu70iltl8n4e\"\n",
    "      },\n",
    "      \"fieldConfig\": {\n",
    "        \"defaults\": {\n",
    "          \"color\": {\n",
    "            \"mode\": \"thresholds\"\n",
    "          },\n",
    "          \"mappings\": [],\n",
    "          \"thresholds\": {\n",
    "            \"mode\": \"absolute\",\n",
    "            \"steps\": [\n",
    "              {\n",
    "                \"color\": \"green\",\n",
    "                \"value\": 0\n",
    "              },\n",
    "              {\n",
    "                \"color\": \"#EAB839\",\n",
    "                \"value\": 8\n",
    "              },\n",
    "              {\n",
    "                \"color\": \"red\",\n",
    "                \"value\": 10\n",
    "              }\n",
    "            ]\n",
    "          },\n",
    "          \"unit\": \"days\"\n",
    "        },\n",
    "        \"overrides\": []\n",
    "      },\n",
    "      \"gridPos\": {\n",
    "        \"h\": 5,\n",
    "        \"w\": 5,\n",
    "        \"x\": 9,\n",
    "        \"y\": 0\n",
    "      },\n",
    "      \"id\": 3,\n",
    "      \"options\": {\n",
    "        \"colorMode\": \"value\",\n",
    "        \"graphMode\": \"area\",\n",
    "        \"justifyMode\": \"auto\",\n",
    "        \"orientation\": \"auto\",\n",
    "        \"percentChangeColorMode\": \"standard\",\n",
    "        \"reduceOptions\": {\n",
    "          \"calcs\": [\n",
    "            \"lastNotNull\"\n",
    "          ],\n",
    "          \"fields\": \"\",\n",
    "          \"values\": false\n",
    "        },\n",
    "        \"showPercentChange\": false,\n",
    "        \"textMode\": \"auto\",\n",
    "        \"wideLayout\": true\n",
    "      },\n",
    "      \"pluginVersion\": \"12.4.2\",\n",
    "      \"targets\": [\n",
    "        {\n",
    "          \"dataset\": \"erp_db\",\n",
    "          \"editorMode\": \"code\",\n",
    "          \"format\": \"table\",\n",
    "          \"rawQuery\": true,\n",
    "          \"rawSql\": \"SELECT AVG(delivery_time_days) AS avg_delivery_time\\nFROM orders_data;\",\n",
    "          \"refId\": \"A\",\n",
    "          \"sql\": {\n",
    "            \"columns\": [\n",
    "              {\n",
    "                \"parameters\": [],\n",
    "                \"type\": \"function\"\n",
    "              }\n",
    "            ],\n",
    "            \"groupBy\": [\n",
    "              {\n",
    "                \"property\": {\n",
    "                  \"type\": \"string\"\n",
    "                },\n",
    "                \"type\": \"groupBy\"\n",
    "              }\n",
    "            ],\n",
    "            \"limit\": 50\n",
    "          }\n",
    "        }\n",
    "      ],\n",
    "      \"title\": \"Average Delivery Time\",\n",
    "      \"type\": \"stat\"\n",
    "    },\n",
    "    {\n",
    "      \"datasource\": {\n",
    "        \"type\": \"grafana-postgresql-datasource\",\n",
    "        \"uid\": \"bfhu70iltl8n4e\"\n",
    "      },\n",
    "      \"fieldConfig\": {\n",
    "        \"defaults\": {\n",
    "          \"color\": {\n",
    "            \"mode\": \"thresholds\"\n",
    "          },\n",
    "          \"mappings\": [],\n",
    "          \"thresholds\": {\n",
    "            \"mode\": \"absolute\",\n",
    "            \"steps\": [\n",
    "              {\n",
    "                \"color\": \"green\",\n",
    "                \"value\": 0\n",
    "              },\n",
    "              {\n",
    "                \"color\": \"#E02F44\",\n",
    "                \"value\": 5000\n",
    "              }\n",
    "            ]\n",
    "          }\n",
    "        },\n",
    "        \"overrides\": []\n",
    "      },\n",
    "      \"gridPos\": {\n",
    "        \"h\": 5,\n",
    "        \"w\": 5,\n",
    "        \"x\": 14,\n",
    "        \"y\": 0\n",
    "      },\n",
    "      \"id\": 4,\n",
    "      \"options\": {\n",
    "        \"colorMode\": \"value\",\n",
    "        \"graphMode\": \"area\",\n",
    "        \"justifyMode\": \"auto\",\n",
    "        \"orientation\": \"auto\",\n",
    "        \"percentChangeColorMode\": \"standard\",\n",
    "        \"reduceOptions\": {\n",
    "          \"calcs\": [\n",
    "            \"lastNotNull\"\n",
    "          ],\n",
    "          \"fields\": \"\",\n",
    "          \"values\": false\n",
    "        },\n",
    "        \"showPercentChange\": false,\n",
    "        \"textMode\": \"auto\",\n",
    "        \"wideLayout\": true\n",
    "      },\n",
    "      \"pluginVersion\": \"12.4.2\",\n",
    "      \"targets\": [\n",
    "        {\n",
    "          \"dataset\": \"erp_db\",\n",
    "          \"editorMode\": \"code\",\n",
    "          \"format\": \"table\",\n",
    "          \"rawQuery\": true,\n",
    "          \"rawSql\": \"SELECT COUNT(*) AS delayed_orders\\nFROM orders_data\\nWHERE is_delayed = TRUE;\",\n",
    "          \"refId\": \"A\",\n",
    "          \"sql\": {\n",
    "            \"columns\": [\n",
    "              {\n",
    "                \"parameters\": [],\n",
    "                \"type\": \"function\"\n",
    "              }\n",
    "            ],\n",
    "            \"groupBy\": [\n",
    "              {\n",
    "                \"property\": {\n",
    "                  \"type\": \"string\"\n",
    "                },\n",
    "                \"type\": \"groupBy\"\n",
    "              }\n",
    "            ],\n",
    "            \"limit\": 50\n",
    "          }\n",
    "        }\n",
    "      ],\n",
    "      \"title\": \"Delayed Orders\",\n",
    "      \"type\": \"stat\"\n",
    "    },\n",
    "    {\n",
    "      \"datasource\": {\n",
    "        \"type\": \"grafana-postgresql-datasource\",\n",
    "        \"uid\": \"bfhu70iltl8n4e\"\n",
    "      },\n",
    "      \"fieldConfig\": {\n",
    "        \"defaults\": {\n",
    "          \"color\": {\n",
    "            \"mode\": \"thresholds\"\n",
    "          },\n",
    "          \"mappings\": [],\n",
    "          \"thresholds\": {\n",
    "            \"mode\": \"absolute\",\n",
    "            \"steps\": [\n",
    "              {\n",
    "                \"color\": \"green\",\n",
    "                \"value\": 0\n",
    "              },\n",
    "              {\n",
    "                \"color\": \"#EAB839\",\n",
    "                \"value\": 5\n",
    "              },\n",
    "              {\n",
    "                \"color\": \"red\",\n",
    "                \"value\": 10\n",
    "              }\n",
    "            ]\n",
    "          },\n",
    "          \"unit\": \"percent\"\n",
    "        },\n",
    "        \"overrides\": []\n",
    "      },\n",
    "      \"gridPos\": {\n",
    "        \"h\": 5,\n",
    "        \"w\": 5,\n",
    "        \"x\": 19,\n",
    "        \"y\": 0\n",
    "      },\n",
    "      \"id\": 7,\n",
    "      \"options\": {\n",
    "        \"colorMode\": \"value\",\n",
    "        \"graphMode\": \"area\",\n",
    "        \"justifyMode\": \"auto\",\n",
    "        \"orientation\": \"auto\",\n",
    "        \"percentChangeColorMode\": \"standard\",\n",
    "        \"reduceOptions\": {\n",
    "          \"calcs\": [\n",
    "            \"lastNotNull\"\n",
    "          ],\n",
    "          \"fields\": \"\",\n",
    "          \"values\": false\n",
    "        },\n",
    "        \"showPercentChange\": false,\n",
    "        \"textMode\": \"auto\",\n",
    "        \"wideLayout\": true\n",
    "      },\n",
    "      \"pluginVersion\": \"12.4.2\",\n",
    "      \"targets\": [\n",
    "        {\n",
    "          \"dataset\": \"erp_db\",\n",
    "          \"editorMode\": \"code\",\n",
    "          \"format\": \"table\",\n",
    "          \"rawQuery\": true,\n",
    "          \"rawSql\": \"SELECT ROUND(100.0 * SUM(CASE WHEN is_delayed = TRUE THEN 1 ELSE 0 END) / COUNT(*),2) \\nAS delayed_order_percentage\\nFROM orders_data;\",\n",
    "          \"refId\": \"A\",\n",
    "          \"sql\": {\n",
    "            \"columns\": [\n",
    "              {\n",
    "                \"parameters\": [],\n",
    "                \"type\": \"function\"\n",
    "              }\n",
    "            ],\n",
    "            \"groupBy\": [\n",
    "              {\n",
    "                \"property\": {\n",
    "                  \"type\": \"string\"\n",
    "                },\n",
    "                \"type\": \"groupBy\"\n",
    "              }\n",
    "            ],\n",
    "            \"limit\": 50\n",
    "          }\n",
    "        }\n",
    "      ],\n",
    "      \"title\": \"Delayed %\",\n",
    "      \"type\": \"stat\"\n",
    "    },\n",
    "    {\n",
    "      \"datasource\": {\n",
    "        \"type\": \"grafana-postgresql-datasource\",\n",
    "        \"uid\": \"bfhu70iltl8n4e\"\n",
    "      },\n",
    "      \"fieldConfig\": {\n",
    "        \"defaults\": {\n",
    "          \"color\": {\n",
    "            \"mode\": \"palette-classic\"\n",
    "          },\n",
    "          \"custom\": {\n",
    "            \"axisBorderShow\": false,\n",
    "            \"axisCenteredZero\": false,\n",
    "            \"axisColorMode\": \"text\",\n",
    "            \"axisLabel\": \"\",\n",
    "            \"axisPlacement\": \"auto\",\n",
    "            \"fillOpacity\": 80,\n",
    "            \"gradientMode\": \"none\",\n",
    "            \"hideFrom\": {\n",
    "              \"legend\": false,\n",
    "              \"tooltip\": false,\n",
    "              \"viz\": false\n",
    "            },\n",
    "            \"lineWidth\": 1,\n",
    "            \"scaleDistribution\": {\n",
    "              \"type\": \"linear\"\n",
    "            },\n",
    "            \"thresholdsStyle\": {\n",
    "              \"mode\": \"off\"\n",
    "            }\n",
    "          },\n",
    "          \"mappings\": [],\n",
    "          \"thresholds\": {\n",
    "            \"mode\": \"absolute\",\n",
    "            \"steps\": [\n",
    "              {\n",
    "                \"color\": \"green\",\n",
    "                \"value\": 0\n",
    "              },\n",
    "              {\n",
    "                \"color\": \"red\",\n",
    "                \"value\": 80\n",
    "              }\n",
    "            ]\n",
    "          }\n",
    "        },\n",
    "        \"overrides\": []\n",
    "      },\n",
    "      \"gridPos\": {\n",
    "        \"h\": 11,\n",
    "        \"w\": 12,\n",
    "        \"x\": 0,\n",
    "        \"y\": 5\n",
    "      },\n",
    "      \"id\": 5,\n",
    "      \"options\": {\n",
    "        \"barRadius\": 0,\n",
    "        \"barWidth\": 0.97,\n",
    "        \"fullHighlight\": false,\n",
    "        \"groupWidth\": 0.7,\n",
    "        \"legend\": {\n",
    "          \"calcs\": [],\n",
    "          \"displayMode\": \"list\",\n",
    "          \"placement\": \"bottom\",\n",
    "          \"showLegend\": true\n",
    "        },\n",
    "        \"orientation\": \"auto\",\n",
    "        \"showValue\": \"always\",\n",
    "        \"stacking\": \"none\",\n",
    "        \"tooltip\": {\n",
    "          \"hideZeros\": false,\n",
    "          \"mode\": \"single\",\n",
    "          \"sort\": \"none\"\n",
    "        },\n",
    "        \"xField\": \"order_status\",\n",
    "        \"xTickLabelRotation\": 45,\n",
    "        \"xTickLabelSpacing\": 0\n",
    "      },\n",
    "      \"pluginVersion\": \"12.4.2\",\n",
    "      \"targets\": [\n",
    "        {\n",
    "          \"dataset\": \"erp_db\",\n",
    "          \"editorMode\": \"code\",\n",
    "          \"format\": \"table\",\n",
    "          \"rawQuery\": true,\n",
    "          \"rawSql\": \"SELECT order_status,COUNT(*) AS total_orders\\nFROM orders_data\\nGROUP BY order_status\\nORDER BY total_orders DESC;\",\n",
    "          \"refId\": \"A\",\n",
    "          \"sql\": {\n",
    "            \"columns\": [\n",
    "              {\n",
    "                \"parameters\": [],\n",
    "                \"type\": \"function\"\n",
    "              }\n",
    "            ],\n",
    "            \"groupBy\": [\n",
    "              {\n",
    "                \"property\": {\n",
    "                  \"type\": \"string\"\n",
    "                },\n",
    "                \"type\": \"groupBy\"\n",
    "              }\n",
    "            ],\n",
    "            \"limit\": 50\n",
    "          }\n",
    "        }\n",
    "      ],\n",
    "      \"title\": \"Orders by Status\",\n",
    "      \"type\": \"barchart\"\n",
    "    },\n",
    "    {\n",
    "      \"datasource\": {\n",
    "        \"type\": \"grafana-postgresql-datasource\",\n",
    "        \"uid\": \"bfhu70iltl8n4e\"\n",
    "      },\n",
    "      \"fieldConfig\": {\n",
    "        \"defaults\": {\n",
    "          \"color\": {\n",
    "            \"mode\": \"palette-classic\"\n",
    "          },\n",
    "          \"custom\": {\n",
    "            \"axisBorderShow\": false,\n",
    "            \"axisCenteredZero\": false,\n",
    "            \"axisColorMode\": \"text\",\n",
    "            \"axisLabel\": \"\",\n",
    "            \"axisPlacement\": \"auto\",\n",
    "            \"fillOpacity\": 80,\n",
    "            \"gradientMode\": \"none\",\n",
    "            \"hideFrom\": {\n",
    "              \"legend\": false,\n",
    "              \"tooltip\": false,\n",
    "              \"viz\": false\n",
    "            },\n",
    "            \"lineWidth\": 1,\n",
    "            \"scaleDistribution\": {\n",
    "              \"type\": \"linear\"\n",
    "            },\n",
    "            \"thresholdsStyle\": {\n",
    "              \"mode\": \"off\"\n",
    "            }\n",
    "          },\n",
    "          \"decimals\": 0,\n",
    "          \"mappings\": [],\n",
    "          \"thresholds\": {\n",
    "            \"mode\": \"absolute\",\n",
    "            \"steps\": [\n",
    "              {\n",
    "                \"color\": \"green\",\n",
    "                \"value\": 0\n",
    "              },\n",
    "              {\n",
    "                \"color\": \"red\",\n",
    "                \"value\": 80\n",
    "              }\n",
    "            ]\n",
    "          },\n",
    "          \"unit\": \"currencyUSD\"\n",
    "        },\n",
    "        \"overrides\": []\n",
    "      },\n",
    "      \"gridPos\": {\n",
    "        \"h\": 11,\n",
    "        \"w\": 12,\n",
    "        \"x\": 12,\n",
    "        \"y\": 5\n",
    "      },\n",
    "      \"id\": 6,\n",
    "      \"options\": {\n",
    "        \"barRadius\": 0,\n",
    "        \"barWidth\": 0.97,\n",
    "        \"fullHighlight\": false,\n",
    "        \"groupWidth\": 0.7,\n",
    "        \"legend\": {\n",
    "          \"calcs\": [],\n",
    "          \"displayMode\": \"list\",\n",
    "          \"placement\": \"bottom\",\n",
    "          \"showLegend\": true\n",
    "        },\n",
    "        \"orientation\": \"auto\",\n",
    "        \"showValue\": \"always\",\n",
    "        \"stacking\": \"none\",\n",
    "        \"tooltip\": {\n",
    "          \"hideZeros\": false,\n",
    "          \"mode\": \"single\",\n",
    "          \"sort\": \"none\"\n",
    "        },\n",
    "        \"xField\": \"customer_state\",\n",
    "        \"xTickLabelRotation\": 45,\n",
    "        \"xTickLabelSpacing\": 0\n",
    "      },\n",
    "      \"pluginVersion\": \"12.4.2\",\n",
    "      \"targets\": [\n",
    "        {\n",
    "          \"dataset\": \"erp_db\",\n",
    "          \"editorMode\": \"code\",\n",
    "          \"format\": \"table\",\n",
    "          \"rawQuery\": true,\n",
    "          \"rawSql\": \"SELECT customer_state,ROUND(SUM(order_total_value)::numeric, 2) AS total_revenue \\nFROM orders_data \\nGROUP BY customer_state \\nORDER BY total_revenue DESC \\nLIMIT 5;\",\n",
    "          \"refId\": \"A\",\n",
    "          \"sql\": {\n",
    "            \"columns\": [\n",
    "              {\n",
    "                \"parameters\": [],\n",
    "                \"type\": \"function\"\n",
    "              }\n",
    "            ],\n",
    "            \"groupBy\": [\n",
    "              {\n",
    "                \"property\": {\n",
    "                  \"type\": \"string\"\n",
    "                },\n",
    "                \"type\": \"groupBy\"\n",
    "              }\n",
    "            ],\n",
    "            \"limit\": 50\n",
    "          }\n",
    "        }\n",
    "      ],\n",
    "      \"title\": \"Revenue by State\",\n",
    "      \"type\": \"barchart\"\n",
    "    }\n",
    "  ],\n",
    "  \"preload\": false,\n",
    "  \"schemaVersion\": 42,\n",
    "  \"tags\": [],\n",
    "  \"templating\": {\n",
    "    \"list\": []\n",
    "  },\n",
    "  \"time\": {\n",
    "    \"from\": \"now-6h\",\n",
    "    \"to\": \"now\"\n",
    "  },\n",
    "  \"timepicker\": {},\n",
    "  \"timezone\": \"browser\",\n",
    "  \"title\": \"E-Commerce Operations Monitoring Dashboard\",\n",
    "  \"uid\": \"ad2l4nx\",\n",
    "  \"version\": 8,\n",
    "  \"weekStart\": \"\"\n",
    "}"
   ]
  }
 ],
 "metadata": {
  "kernelspec": {
   "display_name": "Python (project_env)",
   "language": "python",
   "name": "project_env"
  },
  "language_info": {
   "codemirror_mode": {
    "name": "ipython",
    "version": 3
   },
   "file_extension": ".py",
   "mimetype": "text/x-python",
   "name": "python",
   "nbconvert_exporter": "python",
   "pygments_lexer": "ipython3",
   "version": "3.10.19"
  }
 },
 "nbformat": 4,
 "nbformat_minor": 5
}
